greets/English.py
greets/French.py
greets/Italian.py
greets/Spanish.py
greets/__init__.py
greets-1.0.dist-info/METADATA
greets-1.0.dist-info/WHEEL
greets-1.0.dist-info/top_level.txt
greets-1.0.dist-info/RECORD
