Metadata-Version: 2.1
Name: greets
Version: 1.0
Summary: Greetings from each country
